ccAF/__init__.py
ccAF/actinn.py
ccAF/ccAF_1536_smaller.pkl
ccAF/classifier.py
ccAF-1.0.1.dist-info/LICENSE
ccAF-1.0.1.dist-info/METADATA
ccAF-1.0.1.dist-info/WHEEL
ccAF-1.0.1.dist-info/top_level.txt
ccAF-1.0.1.dist-info/RECORD
