Metadata-Version: 2.1
Name: ccAF
Version: 1.0.1
Summary: Classify scRNA-seq profiling with highly resolved cell cycle phases.
Home-page: https://github.com/plaisier-lab/ccAF
Author: Christopher Plaisier
Author-email: plaisier@asu.edu
License: GNU General Public License v3.0
Platform: UNKNOWN
Classifier: License :: OSI Approved :: GNU Affero General Public License v3
Classifier: Topic :: Scientific/Engineering :: Bio-Informatics
Classifier: Topic :: Scientific/Engineering :: Medical Science Apps.
Classifier: Programming Language :: Python :: 3
Classifier: Programming Language :: Python :: 3.7
Requires-Dist: numpy
Requires-Dist: scipy
Requires-Dist: pandas
Requires-Dist: tensorflow
